psp_auth/__init__.py
psp_auth/cache.py
psp_auth/config.py
psp_auth/core.py
psp_auth/endpoints.py
psp_auth/errors.py
psp_auth/token.py
psp_auth/user.py
psp_auth/fastapi/__init__.py
psp_auth/fastapi/auth.py
psp_auth/testing/__init__.py
psp_auth-1.1.0.dist-info/licenses/LICENSE
psp_auth-1.1.0.dist-info/METADATA
psp_auth-1.1.0.dist-info/WHEEL
psp_auth-1.1.0.dist-info/top_level.txt
psp_auth-1.1.0.dist-info/RECORD
