Metadata-Version: 2.4
Name: psp-auth
Version: 1.1.0
Summary: A Python library for authentication and authorisation in the PSP platform
License: MIT License
Project-URL: Homepage, https://github.com/Portfolio-Solver-Platform/python-auth-lib
Keywords: psp,auth,authentication,authorisation,authorization
Classifier: License :: OSI Approved :: MIT License
Classifier: Programming Language :: Python
Classifier: Programming Language :: Python :: 3
Requires-Python: >=3.12
License-File: LICENSE
Requires-Dist: joserfc<2.0,>=1.3.4
Requires-Dist: fastapi[standard]<0.121,>=0.120.1
Requires-Dist: httpx<0.29.0,>=0.28.1
Requires-Dist: itsdangerous<3.0,>=2.2.0
Provides-Extra: dev
Requires-Dist: pytest<9,>=8; extra == "dev"
Requires-Dist: pytest-cov<8,>=7; extra == "dev"
Requires-Dist: ruff<0.14.0,>=0.13.2; extra == "dev"
Requires-Dist: bandit<2.0,>=1.7; extra == "dev"
Requires-Dist: pip-audit<3.0,>=2.7; extra == "dev"
Requires-Dist: pytest-asyncio<=2.0,>=1.2.0; extra == "dev"
Dynamic: license-file
